CHANGES.txt
LICENCE.txt
MANIFEST.in
README.rst
requirements.txt
runtests.py
setup.py
pois/PhaseScreen.py
pois/Zernike.py
pois/__init__.py
pois.egg-info/PKG-INFO
pois.egg-info/SOURCES.txt
pois.egg-info/dependency_links.txt
pois.egg-info/requires.txt
pois.egg-info/top_level.txt
tests/test_ao.py
tests/test_fibre.py
tests/test_visibility.py