Metadata-Version: 1.1
Name: pois
Version: 0.3.0
Summary: Python optical interferometer simulation
Home-page: http://github.com/dbuscher/pois/
Author: David Buscher
Author-email: dfb@mrao.cam.ac.uk
License: UNKNOWN
Platform: any
Classifier: Programming Language :: Python :: 3
Classifier: Development Status :: 4 - Beta
Classifier: Natural Language :: English
Classifier: Intended Audience :: Science/Research
Classifier: License :: OSI Approved :: BSD License
Classifier: Operating System :: OS Independent
Classifier: Topic :: Scientific/Engineering :: Astronomy
Classifier: Topic :: Scientific/Engineering :: Physics
